postcode_to_timezone.py
postcode_regex.json
postcode_to_timezone_lookup.csv
postcode_to_timezone-2024.11.27.5.dist-info/METADATA
postcode_to_timezone-2024.11.27.5.dist-info/WHEEL
postcode_to_timezone-2024.11.27.5.dist-info/licenses/LICENSE
postcode_to_timezone-2024.11.27.5.dist-info/RECORD
