Metadata-Version: 2.3
Name: postcode-to-timezone
Version: 2024.11.27.5
Summary: Converts postcodes to timezones
Project-URL: repository, https://github.com/kvdveer/postcode-to-timezone
Author-email: Koert van der Veer <pypi@ondergetekende.nl>
Maintainer-email: Koert van der Veer <pypi@ondergetekende.nl>
License: MIT
Keywords: open street map,time zone
Classifier: Development Status :: 5 - Production/Stable
Classifier: Intended Audience :: Developers
Classifier: License :: OSI Approved :: MIT License
Classifier: Programming Language :: Python :: 3
Classifier: Programming Language :: Python :: 3.8
Classifier: Programming Language :: Python :: 3.9
Classifier: Programming Language :: Python :: 3.10
Classifier: Programming Language :: Python :: 3.11
Classifier: Programming Language :: Python :: 3.12
